hotpartners_twofa/__init__.py
hotpartners_twofa/cli.py
hotpartners_twofa/config.py
hotpartners_twofa/decorator.py
hotpartners_twofa/exceptions.py
hotpartners_twofa/models.py
hotpartners_twofa/repository.py
hotpartners_twofa/schema.py
hotpartners_twofa/service.py
hotpartners_twofa/setup.py
hotpartners_twofa/sql/schema.sql
hotpartners_twofa-1.1.2.dist-info/LICENSE
hotpartners_twofa-1.1.2.dist-info/METADATA
hotpartners_twofa-1.1.2.dist-info/WHEEL
hotpartners_twofa-1.1.2.dist-info/entry_points.txt
hotpartners_twofa-1.1.2.dist-info/top_level.txt
hotpartners_twofa-1.1.2.dist-info/RECORD
