Metadata-Version: 2.1
Name: hotpartners-twofa
Version: 1.1.2
Summary: Two-Factor Authentication (2FA) package for HotPartners
Home-page: https://pypi.org/project/hotpartners-twofa/
Author: hotseller_devjun
Author-email: jypark@hotseller.co.kr
Project-URL: Homepage, https://pypi.org/project/hotpartners-twofa/
Keywords: 2fa two-factor authentication otp totp qr-code security
Classifier: Development Status :: 5 - Production/Stable
Classifier: Intended Audience :: Developers
Classifier: Operating System :: OS Independent
Classifier: Programming Language :: Python :: 3
Classifier: Programming Language :: Python :: 3.8
Classifier: Programming Language :: Python :: 3.9
Classifier: Programming Language :: Python :: 3.10
Classifier: Programming Language :: Python :: 3.11
Classifier: Topic :: Software Development :: Libraries :: Python Modules
Classifier: Topic :: Security
Requires-Python: >=3.8
License-File: LICENSE
Requires-Dist: pyotp>=2.9.0
Requires-Dist: qrcode[pil]>=7.4.2
Requires-Dist: cryptography>=41.0.7
Requires-Dist: pillow>=11.3.0
Provides-Extra: dev
Requires-Dist: pytest>=6.0; extra == "dev"
Requires-Dist: pytest-asyncio>=0.21.0; extra == "dev"
Requires-Dist: black>=22.0; extra == "dev"
Requires-Dist: flake8>=4.0; extra == "dev"
Requires-Dist: mypy>=0.950; extra == "dev"
Provides-Extra: docs
Requires-Dist: sphinx>=4.0; extra == "docs"
Requires-Dist: sphinx-rtd-theme>=1.0; extra == "docs"
